setup.py
tgext/__init__.py
tgext.wdb.egg-info/PKG-INFO
tgext.wdb.egg-info/SOURCES.txt
tgext.wdb.egg-info/dependency_links.txt
tgext.wdb.egg-info/entry_points.txt
tgext.wdb.egg-info/namespace_packages.txt
tgext.wdb.egg-info/not-zip-safe
tgext.wdb.egg-info/requires.txt
tgext.wdb.egg-info/top_level.txt
tgext/wdb/__init__.py
tgext/wdb/wdb_support.py